eventure/__init__.py
eventure/event.py
eventure/event_bus.py
eventure/event_log.py
eventure/event_query.py
eventure-0.4.4.dist-info/METADATA
eventure-0.4.4.dist-info/WHEEL
eventure-0.4.4.dist-info/licenses/LICENSE
eventure-0.4.4.dist-info/RECORD
