Metadata-Version: 2.4
Name: eventure
Version: 0.4.4
Summary: A Python library providing a robust, type-safe event system for game development and simulation.
Author-email: Enrico Stara <enrico.stara@gmail.com>
License: MIT License
License-File: LICENSE
Requires-Python: >=3.12
